uncertainties_pandas/__init__.py
uncertainties_pandas/uncertainty_array.py
uncertainties_pandas/testsuite/test_uncertainties.py
Uncertainties_Pandas-0.1.2.dist-info/AUTHORS
Uncertainties_Pandas-0.1.2.dist-info/LICENSE
Uncertainties_Pandas-0.1.2.dist-info/METADATA
Uncertainties_Pandas-0.1.2.dist-info/WHEEL
Uncertainties_Pandas-0.1.2.dist-info/top_level.txt
Uncertainties_Pandas-0.1.2.dist-info/RECORD
